tdstyles/__init__.py
tdstyles/easy_plots.py
tdstyles/style_css.py
tdstyles-0.0.7.dist-info/LICENCE.txt
tdstyles-0.0.7.dist-info/METADATA
tdstyles-0.0.7.dist-info/WHEEL
tdstyles-0.0.7.dist-info/top_level.txt
tdstyles-0.0.7.dist-info/RECORD
