Metadata-Version: 2.1
Name: tdstyles
Version: 0.0.7
Summary: A python package which helps in customizing a jupyter notebook with very less effort.
Home-page: https://sprakshith.pythonanywhere.com/
Author: SP RAKSHITH
Author-email: rakshith0908@gmail.com
License: MIT
Keywords: matplotlib pyplot seaborn plt sns
Platform: UNKNOWN
Classifier: Development Status :: 3 - Alpha
Classifier: Operating System :: OS Independent
Classifier: License :: OSI Approved :: MIT License
Classifier: Programming Language :: Python :: 3
Classifier: Intended Audience :: Developers
License-File: LICENCE.txt
Requires-Dist: matplotlib
Requires-Dist: IPython
Requires-Dist: seaborn
